README.rst
setup.py
dfbgn/__init__.py
dfbgn/diagnostic_info.py
dfbgn/exit_information.py
dfbgn/hessian.py
dfbgn/model.py
dfbgn/params.py
dfbgn/solver.py
dfbgn/trust_region.py
dfbgn/util.py
dfbgn/version.py
dfbgn.egg-info/PKG-INFO
dfbgn.egg-info/SOURCES.txt
dfbgn.egg-info/dependency_links.txt
dfbgn.egg-info/requires.txt
dfbgn.egg-info/top_level.txt
dfbgn.egg-info/zip-safe