Metadata-Version: 1.1
Name: dfbgn
Version: 0.1
Summary: A derivative-free solver for large-scale nonlinear least-squares minimization
Home-page: https://github.com/numericalalgorithmsgroup/dfbgn/
Author: Lindon Roberts
Author-email: lindon.roberts@anu.edu.au
License: GNU GPL
Download-URL: https://github.com/numericalalgorithmsgroup/dfbgn/archive/v0.1.tar.gz
Keywords: mathematics derivative free optimization nonlinear least squares
Platform: UNKNOWN
Classifier: Development Status :: 5 - Production/Stable
Classifier: Environment :: Console
Classifier: Framework :: IPython
Classifier: Framework :: Jupyter
Classifier: Intended Audience :: Financial and Insurance Industry
Classifier: Intended Audience :: Science/Research
Classifier: License :: OSI Approved :: GNU General Public License (GPL)
Classifier: Operating System :: MacOS
Classifier: Operating System :: Microsoft :: Windows
Classifier: Operating System :: POSIX
Classifier: Operating System :: Unix
Classifier: Programming Language :: Python
Classifier: Programming Language :: Python :: 2
Classifier: Programming Language :: Python :: 3
Classifier: Topic :: Scientific/Engineering
Classifier: Topic :: Scientific/Engineering :: Mathematics
